{
  "basin": "WPAC",
  "lastUpdate": "2025-12-06T12:31:05.313Z",
  "systems": [
    {
      "id": "32W",
      "name": "FUNG WONG",
      "year": 2025,
      "basin": "WPAC",
      "center": "ECMWF",
      "advisoryTime": "2025-11-13 00Z · offset D-8",
      "strikeUrl": "https://charts.ecmwf.int/products/cyclone?base_time=202511130000&offset=D-8&product=tc_strike_aifs_ens&unique_id=32W_FUNGWONG_2025",
      "plumesUrl": "https://charts.ecmwf.int/products/cyclone?base_time=202511130000&offset=D-8&product=tc_plumes_aifs_ens&unique_id=32W_FUNGWONG_2025"
    }
  ]
}